{
    "routeType":  "AssignRouteType_RB_Draw",
    "exported":  "true",
    "guid":  "d9a4f3e8-949f-4621-8510-6bc595446e45",
    "steps":  [
                  {
                      "exported":  "true",
                      "guid":  "d523b664-8b14-4c94-9914-ac1d6c85e7b9",
                      "data":  {
                                   "opCodeEX":  "ID_CANNEDHANDOFF",
                                   "handoffAnim":  "176",
                                   "playerNum":  "HandoffPlayerSlot_O1",
                                   "flippedHandoffAnim":  "177"
                               },
                      "type":  "CannedHandoffAssignment"
                  },
                  {
                      "exported":  "true",
                      "guid":  "6dff8eb3-c38c-4fb5-8135-daff91c40153",
                      "data":  {
                                   "optionalInitalDirection":  "-1",
                                   "opCodeEX":  "ID_INITIALMOVE",
                                   "anim":  "MOVETYPE_HB_LATERAL_STEP",
                                   "direction":  "10"
                               },
                      "type":  "InitialAnimAssignment"
                  },
                  {
                      "exported":  "true",
                      "guid":  "5ec15c05-a0b7-456b-bb97-dd2646f4cfdc",
                      "data":  {
                                   "overrideFacingDirection":  "false",
                                   "direction":  "0",
                                   "distance":  "1",
                                   "facingDirectionOverride":  "0",
                                   "speed":  "1",
                                   "opCodeEX":  "ID_RECHANDOFF"
                               },
                      "type":  "ReceiveHandoffAssignment"
                  },
                  {
                      "exported":  "true",
                      "guid":  "40d5168f-d6fa-4ef2-8fa1-c259669f2e1a",
                      "data":  {
                                   "overrideFacingDirection":  "false",
                                   "direction":  "33",
                                   "distance":  "2",
                                   "facingDirectionOverride":  "0",
                                   "speed":  "100",
                                   "opCodeEX":  "ID_MOVEDIRDIST"
                               },
                      "type":  "MoveDirectionAssignment"
                  },
                  {
                      "exported":  "true",
                      "guid":  "c285ba2f-8876-4415-b1e6-2aaf63d9d576",
                      "data":  {
                                   "opCodeEX":  "ID_RUNEZ"
                               },
                      "type":  "RunEndZoneAssignment"
                  },
                  {
                      "exported":  "true",
                      "guid":  "f24744ef-9a7a-40ee-977f-cc7346026457",
                      "data":  {
                                   "opCodeEX":  "ID_NONE"
                               },
                      "type":  "NoneAssignment"
                  }
              ],
    "name":  "football/Gameplay/playbooks/PlayLibrary/Assignments/Halfback/SG2RB_H4_Delay_Backstep_Hand_Statue"
}
