{
    "routeType":  "AssignRouteType_RB_Dive",
    "exported":  "true",
    "guid":  "660017d0-9842-4c0a-b311-a3d75c576567",
    "steps":  [
                  {
                      "exported":  "true",
                      "guid":  "3ac3d48a-4e6b-4234-9eab-8b7494c7f214",
                      "data":  {
                                   "opCodeEX":  "ID_CANNEDHANDOFF",
                                   "handoffAnim":  "37",
                                   "playerNum":  "HandoffPlayerSlot_O1",
                                   "flippedHandoffAnim":  "38"
                               },
                      "type":  "CannedHandoffAssignment"
                  },
                  {
                      "exported":  "true",
                      "guid":  "6e97c8f9-a797-4f61-8b38-1a9bab68436f",
                      "data":  {
                                   "overrideFacingDirection":  "false",
                                   "direction":  "100",
                                   "distance":  "5",
                                   "facingDirectionOverride":  "0",
                                   "speed":  "75",
                                   "opCodeEX":  "ID_RECHANDOFF"
                               },
                      "type":  "ReceiveHandoffAssignment"
                  },
                  {
                      "exported":  "true",
                      "guid":  "5c3533db-5bef-4eb9-b3f6-13db1ca4455f",
                      "data":  {
                                   "opCodeEX":  "ID_RUNEZ"
                               },
                      "type":  "RunEndZoneAssignment"
                  },
                  {
                      "exported":  "true",
                      "guid":  "c4ed845a-f570-492b-ad3f-84942c8ddd4a",
                      "data":  {
                                   "opCodeEX":  "ID_NONE"
                               },
                      "type":  "NoneAssignment"
                  }
              ],
    "name":  "football/Gameplay/playbooks/PlayLibrary/Assignments/Fullback/Flexbone_FB_Trap_LT_Precan_37_38"
}
