{
    "routeType":  "AssignRouteType_Block_Run",
    "exported":  "true",
    "guid":  "13280ca2-7b42-49bb-af7c-c29e04f65c38",
    "steps":  [
                  {
                      "exported":  "true",
                      "guid":  "d943cd4c-cc64-4793-a307-9397da73c8b0",
                      "data":  {
                                   "optionalInitalDirection":  "-1",
                                   "opCodeEX":  "ID_INITIALMOVE",
                                   "anim":  "MOVETYPE_TRAP_PULL",
                                   "direction":  "172"
                               },
                      "type":  "InitialAnimAssignment"
                  },
                  {
                      "exported":  "true",
                      "guid":  "c15b9486-ede8-48f3-b54b-27aebd38cd6e",
                      "data":  {
                                   "blockingGap":  "RUN_HOLE",
                                   "opCodeEX":  "ID_LEADBLOCK",
                                   "blockingTechnique":  "BLOCKINGTECHNIQUE_LEAD_HOLE_LAST"
                               },
                      "type":  "LeadBlockAssignment"
                  },
                  {
                      "exported":  "true",
                      "guid":  "5a5706bb-0ef0-49c8-a3c7-98cde89a0e84",
                      "data":  {
                                   "opCodeEX":  "ID_NONE"
                               },
                      "type":  "NoneAssignment"
                  }
              ],
    "name":  "football/Gameplay/playbooks/PlayLibrary/Assignments/Blocking/TE_Pull_H9_Deep_Counter_Wk_Lead"
}
