{
    "routeType":  "AssignRouteType_RR_Wheel_Lt",
    "exported":  "true",
    "guid":  "ff2d0583-f6b4-4dae-895d-f1eef005951f",
    "steps":  [
                  {
                      "exported":  "true",
                      "guid":  "21dd4375-3827-462d-92ec-1d0882f6fb4f",
                      "data":  {
                                   "waypoints":  [
                                                     "-5-618590AUTOMOTIONLOCOSTYLE_NORMALtrue",
                                                     "-2.9-618590AUTOMOTIONLOCOSTYLE_NORMALtrue"
                                                 ],
                                   "shouldStopAtTarget":  "true",
                                   "automotionOrderPlayer":  "0",
                                   "startDelay":  "0",
                                   "useLegacyLocoPathing":  "true",
                                   "endDelay":  "0.2",
                                   "stanceAtTarget":  "StanceType_2pt_HB",
                                   "opCodeEX":  "ID_AUTOMOTION",
                                   "startEvent":  "AUTOMOTIONSTARTEVENT_SNAP",
                                   "automotionOrderTransitID":  "1"
                               },
                      "type":  "AutoMotionAssignment"
                  },
                  {
                      "exported":  "true",
                      "guid":  "d2fd3d0e-c938-4ec6-bc48-45cda4383dd0",
                      "data":  {
                                   "overrideFacingDirection":  "false",
                                   "direction":  "170",
                                   "distance":  "12",
                                   "facingDirectionOverride":  "0",
                                   "speed":  "100",
                                   "opCodeEX":  "ID_RUNROUTE"
                               },
                      "type":  "RunRouteAssignment"
                  },
                  {
                      "exported":  "true",
                      "guid":  "83c5bb2e-7b55-4a4b-90b7-a463185cebab",
                      "data":  {
                                   "overrideFacingDirection":  "false",
                                   "direction":  "110",
                                   "distance":  "30",
                                   "facingDirectionOverride":  "0",
                                   "speed":  "100",
                                   "opCodeEX":  "ID_RUNROUTE"
                               },
                      "type":  "RunRouteAssignment"
                  },
                  {
                      "exported":  "true",
                      "guid":  "40b315bf-927d-4041-9f81-c5235443bbe3",
                      "data":  {
                                   "opCodeEX":  "ID_RECGETOPEN"
                               },
                      "type":  "GetOpenAssignment"
                  },
                  {
                      "exported":  "true",
                      "guid":  "873ce712-6cf3-4a45-a845-c1659ad59e87",
                      "data":  {
                                   "opCodeEX":  "ID_NONE"
                               },
                      "type":  "NoneAssignment"
                  }
              ],
    "name":  "football/Gameplay/playbooks/PlayLibrary/Assignments/Screen/HB_Automotion_Reload_toGunEven_Lt_HBWheelLt"
}
