{
    "routeType":  "AssignRouteType_RR_Option_Hitch_In_Out",
    "exported":  "true",
    "guid":  "27a62c6e-bb53-4eeb-85a9-7062552d51b4",
    "steps":  [
                  {
                      "exported":  "true",
                      "guid":  "23c2ddf6-3aab-49e0-9f8a-a01739eff775",
                      "data":  {
                                   "waypoints":  [
                                                     "-3-2.50500AUTOMOTIONLOCOSTYLE_NORMALtrue",
                                                     "-5-2.503090AUTOMOTIONLOCOSTYLE_STRAFEfalse"
                                                 ],
                                   "shouldStopAtTarget":  "false",
                                   "automotionOrderPlayer":  "0",
                                   "startDelay":  "0",
                                   "useLegacyLocoPathing":  "false",
                                   "endDelay":  "0",
                                   "stanceAtTarget":  "StanceType_None",
                                   "opCodeEX":  "ID_AUTOMOTION",
                                   "startEvent":  "AUTOMOTIONSTARTEVENT_SNAP",
                                   "automotionOrderTransitID":  "1"
                               },
                      "type":  "AutoMotionAssignment"
                  },
                  {
                      "exported":  "true",
                      "guid":  "c2d56e6a-966c-4bdc-ad97-7dbed8404275",
                      "data":  {
                                   "overrideFacingDirection":  "false",
                                   "direction":  "90",
                                   "distance":  "3.5",
                                   "facingDirectionOverride":  "0",
                                   "speed":  "100",
                                   "opCodeEX":  "ID_RUNROUTE"
                               },
                      "type":  "RunRouteAssignment"
                  },
                  {
                      "exported":  "true",
                      "guid":  "7bdf7437-e92b-4161-a6b8-18f835d18313",
                      "data":  {
                                   "optionRouteInfo":  [
                                                           "e581ee8e-c3d6-405c-8ac2-f181d79eb875OptionRouteCoverage_Default",
                                                           "1a21272b-8677-4987-824d-b65b811318c5OptionRouteCoverage_Cover4",
                                                           "a5e5732a-cc40-4655-8534-46b53b68c189143"
                                                       ],
                                   "opCodeEX":  "ID_OPTIONROUTE"
                               },
                      "type":  "OptionRouteAssignment"
                  },
                  {
                      "exported":  "true",
                      "guid":  "fb15fd36-1d89-44a5-abec-e800ae10c1bb",
                      "data":  {
                                   "opCodeEX":  "ID_RECGETOPEN"
                               },
                      "type":  "GetOpenAssignment"
                  },
                  {
                      "exported":  "true",
                      "guid":  "7ede1077-fe55-4218-aae6-cff9629d2ce4",
                      "data":  {
                                   "opCodeEX":  "ID_NONE"
                               },
                      "type":  "NoneAssignment"
                  }
              ],
    "name":  "football/Gameplay/playbooks/PlayLibrary/Assignments/RunRoute/Automotion_X-5_Option_WR_Choice_In_or_Out_Left_Slot"
}
