{
    "routeType":  "AssignRouteType_RR_Swing_Lt",
    "exported":  "true",
    "guid":  "4eaeed29-df42-42e9-9e22-d03373e59b2a",
    "steps":  [
                  {
                      "exported":  "true",
                      "guid":  "dc990815-ecf8-4a58-a91a-145c1cff8d42",
                      "data":  {
                                   "waypoints":  [
                                                     "3-8110090AUTOMOTIONLOCOSTYLE_NORMALtrue",
                                                     "-1.5-8110090AUTOMOTIONLOCOSTYLE_NORMALtrue"
                                                 ],
                                   "shouldStopAtTarget":  "false",
                                   "automotionOrderPlayer":  "0",
                                   "startDelay":  "0",
                                   "useLegacyLocoPathing":  "false",
                                   "endDelay":  "0",
                                   "stanceAtTarget":  "StanceType_None",
                                   "opCodeEX":  "ID_AUTOMOTION",
                                   "startEvent":  "AUTOMOTIONSTARTEVENT_SNAP",
                                   "automotionOrderTransitID":  "1"
                               },
                      "type":  "AutoMotionAssignment"
                  },
                  {
                      "exported":  "true",
                      "guid":  "52421ca2-3454-473d-b923-7480797c437f",
                      "data":  {
                                   "overrideFacingDirection":  "false",
                                   "direction":  "167",
                                   "distance":  "17",
                                   "facingDirectionOverride":  "0",
                                   "speed":  "75",
                                   "opCodeEX":  "ID_RUNROUTE"
                               },
                      "type":  "RunRouteAssignment"
                  },
                  {
                      "exported":  "true",
                      "guid":  "96e0bcd2-7162-4477-956f-bd37f619c911",
                      "data":  {
                                   "landingZoneKickoffDelay":  "false",
                                   "opCodeEX":  "ID_DELAY",
                                   "time":  "2.5",
                                   "timeNGPM":  "0"
                               },
                      "type":  "DelayAssignment"
                  },
                  {
                      "exported":  "true",
                      "guid":  "6a53426d-c2e6-4f70-a4c5-1e2cd1509bf9",
                      "data":  {
                                   "opCodeEX":  "ID_RECGETOPEN"
                               },
                      "type":  "GetOpenAssignment"
                  },
                  {
                      "exported":  "true",
                      "guid":  "c525a6c1-24cb-4c5f-80ab-20afe174812c",
                      "data":  {
                                   "opCodeEX":  "ID_NONE"
                               },
                      "type":  "NoneAssignment"
                  }
              ],
    "name":  "football/Gameplay/playbooks/PlayLibrary/Assignments/RunRoute/Automotion_HB_Bunch_Orbit_LT"
}
