{
    "routeType":  "AssignRouteType_RR_Option_Route",
    "exported":  "true",
    "guid":  "f70a3f8d-835c-4256-a118-2a02cd9891b2",
    "steps":  [
                  {
                      "exported":  "true",
                      "guid":  "6e240906-1eaa-40b6-9077-dd43bd157193",
                      "data":  {
                                   "overrideFacingDirection":  "false",
                                   "direction":  "90",
                                   "distance":  "10",
                                   "facingDirectionOverride":  "0",
                                   "speed":  "100",
                                   "opCodeEX":  "ID_RUNROUTE"
                               },
                      "type":  "RunRouteAssignment"
                  },
                  {
                      "exported":  "true",
                      "guid":  "3f1efe60-69c9-4c0b-9388-9ec731823174",
                      "data":  {
                                   "optionRouteInfo":  [
                                                           "0b44f40d-df56-43f7-8605-463773a59f16OptionRouteCoverage_Default",
                                                           "4ab30846-46b3-4490-86e7-f4067736a863OptionRouteCoverage_Cover3",
                                                           "1a21272b-8677-4987-824d-b65b811318c5143"
                                                       ],
                                   "opCodeEX":  "ID_OPTIONROUTE"
                               },
                      "type":  "OptionRouteAssignment"
                  },
                  {
                      "exported":  "true",
                      "guid":  "1bbbe644-aa04-4d2b-baa8-bb13d51cca17",
                      "data":  {
                                   "opCodeEX":  "ID_NONE"
                               },
                      "type":  "NoneAssignment"
                  }
              ],
    "name":  "football/Gameplay/playbooks/PlayLibrary/Assignments/RunRoute/Option_Hitch_Out_Fade_LT"
}
