{
    "play":  {
                 "namePath":  "football/Gameplay/playbooks/PlayLibrary/Formations/Offense/I_Form/Pro/Off_Tackle",
                 "playName":  "Off Tackle",
                 "playId":  950,
                 "situation":  "GeneralPurpose",
                 "guid":  "d2df6964-8ffa-4b80-a470-661b0129b5be",
                 "offensePlayType":  "OffensePlayType_RunOutsideZone",
                 "flowType":  "FlowType_SplitFlow",
                 "formation":  null,
                 "defensePlayType":  "DefensePlayType_DontCare",
                 "exported":  "true",
                 "blockingScheme":  "football/Gameplay/playbooks/PlayLibrary/Blocking/BTOutsideZone\\\\3a7c5842-ba57-4b9c-bf84-6b647984a61c",
                 "runFitsCount":  0
             },
    "assignments":  [
                        {
                            "exported":  null,
                            "guid":  "football/Gameplay/playbooks/PlayLibrary/Assignments/Precan/QB_UC_HB_OutsideZoneRt_BootLt_Hand_Precan_113_111\\\\7220a558-c6d8-4293-b771-4f75a2c36b3d",
                            "data":  {

                                     },
                            "type":  null
                        },
                        {
                            "exported":  null,
                            "guid":  "football/Gameplay/playbooks/PlayLibrary/Assignments/Halfback/SB_H4_Delay_Backstep_Hand\\\\44cd5116-5986-4949-a132-b80fc8841f3c",
                            "data":  {

                                     },
                            "type":  null
                        },
                        {
                            "exported":  null,
                            "guid":  "football/Gameplay/playbooks/PlayLibrary/Assignments/Blocking/FB_IForm_H4_LeadHoleLast\\\\dc4c0bed-f97f-4c40-974d-34fa70b98b98",
                            "data":  {

                                     },
                            "type":  null
                        },
                        {
                            "exported":  null,
                            "guid":  "football/Gameplay/playbooks/PlayLibrary/Assignments/Blocking/RunBlock_All\\\\c4e841c7-8c31-464f-b760-d48cd568143d",
                            "data":  {

                                     },
                            "type":  null
                        },
                        {
                            "exported":  null,
                            "guid":  "football/Gameplay/playbooks/PlayLibrary/Assignments/Blocking/RunBlock_All\\\\c4e841c7-8c31-464f-b760-d48cd568143d",
                            "data":  {

                                     },
                            "type":  null
                        },
                        {
                            "exported":  null,
                            "guid":  "football/Gameplay/playbooks/PlayLibrary/Assignments/Blocking/RunBlock_All\\\\c4e841c7-8c31-464f-b760-d48cd568143d",
                            "data":  {

                                     },
                            "type":  null
                        },
                        {
                            "exported":  null,
                            "guid":  "football/Gameplay/playbooks/PlayLibrary/Assignments/Blocking/RunBlock_All\\\\c4e841c7-8c31-464f-b760-d48cd568143d",
                            "data":  {

                                     },
                            "type":  null
                        },
                        {
                            "exported":  null,
                            "guid":  "football/Gameplay/playbooks/PlayLibrary/Assignments/Blocking/RunBlock_All\\\\c4e841c7-8c31-464f-b760-d48cd568143d",
                            "data":  {

                                     },
                            "type":  null
                        },
                        {
                            "exported":  null,
                            "guid":  "football/Gameplay/playbooks/PlayLibrary/Assignments/Blocking/RunBlock_All\\\\c4e841c7-8c31-464f-b760-d48cd568143d",
                            "data":  {

                                     },
                            "type":  null
                        },
                        {
                            "exported":  null,
                            "guid":  "football/Gameplay/playbooks/PlayLibrary/Assignments/Blocking/RunBlock_All\\\\c4e841c7-8c31-464f-b760-d48cd568143d",
                            "data":  {

                                     },
                            "type":  null
                        },
                        {
                            "exported":  null,
                            "guid":  "football/Gameplay/playbooks/PlayLibrary/Assignments/Blocking/RunBlock_All\\\\c4e841c7-8c31-464f-b760-d48cd568143d",
                            "data":  {

                                     },
                            "type":  null
                        }
                    ]
}
