{
    "routeType":  "AssignRouteType_RR_In_Middle",
    "exported":  "true",
    "guid":  "0e1ef1d3-d69d-4fac-bf28-82607ddcf98c",
    "steps":  [
                  {
                      "exported":  "true",
                      "guid":  "460c9827-17c3-4d35-9084-531ae6d91411",
                      "data":  {
                                   "flags":  "PassBlockFlags_None",
                                   "opCodeEX":  "ID_PASSBLOCK",
                                   "time":  "0.5"
                               },
                      "type":  "PassBlockAssignment"
                  },
                  {
                      "exported":  "true",
                      "guid":  "91654800-8cb3-4cb2-ab61-fdadce28444f",
                      "data":  {
                                   "overrideFacingDirection":  "false",
                                   "direction":  "70",
                                   "distance":  "5",
                                   "facingDirectionOverride":  "0",
                                   "speed":  "100",
                                   "opCodeEX":  "ID_RUNROUTE"
                               },
                      "type":  "RunRouteAssignment"
                  },
                  {
                      "exported":  "true",
                      "guid":  "07928e5d-30dc-4118-baf8-7bcb8f55693b",
                      "data":  {
                                   "cutType":  "RECEIVER_CUT_ANGLE_67",
                                   "opCodeEX":  "ID_RECCUT",
                                   "direction":  "RECEIVER_CUT_DIR_RIGHT"
                               },
                      "type":  "ReceiverCutAssignment"
                  },
                  {
                      "exported":  "true",
                      "guid":  "8c8b8297-228c-4177-91b2-f353c219b22f",
                      "data":  {
                                   "overrideFacingDirection":  "false",
                                   "direction":  "0",
                                   "distance":  "15",
                                   "facingDirectionOverride":  "0",
                                   "speed":  "100",
                                   "opCodeEX":  "ID_RUNROUTE"
                               },
                      "type":  "RunRouteAssignment"
                  },
                  {
                      "exported":  "true",
                      "guid":  "b464220e-6e6c-41e1-92b0-ebc72fa06d8b",
                      "data":  {
                                   "opCodeEX":  "ID_RECGETOPEN"
                               },
                      "type":  "GetOpenAssignment"
                  },
                  {
                      "exported":  "true",
                      "guid":  "b97d24f6-3030-4c58-9992-b102c07ef8b6",
                      "data":  {
                                   "opCodeEX":  "ID_NONE"
                               },
                      "type":  "NoneAssignment"
                  }
              ],
    "name":  "football/Gameplay/playbooks/PlayLibrary/Assignments/RunRoute/HB_Block_QuickOut_Rt"
}
