{
    "routeType":  "AssignRouteType_QB_Handoff",
    "exported":  "true",
    "guid":  "091fb456-6856-4f34-8ea2-5f97fed9e8f6",
    "steps":  [
                  {
                      "exported":  "true",
                      "guid":  "6b09ed84-3a05-4c9f-99e2-368b490f4685",
                      "data":  {
                                   "opCodeEX":  "ID_CANNEDHANDOFF",
                                   "handoffAnim":  "46",
                                   "playerNum":  "HandoffPlayerSlot_SNAP_RECEIVER",
                                   "flippedHandoffAnim":  "50"
                               },
                      "type":  "CannedHandoffAssignment"
                  },
                  {
                      "exported":  "true",
                      "guid":  "25908e2a-278f-43dd-967e-d042fb0ef134",
                      "data":  {
                                   "speed":  "1",
                                   "opCodeEX":  "ID_HANDOFF_TURN",
                                   "TurnDirection":  "TURN_LEFT",
                                   "direction":  "145",
                                   "BallHand":  "BALLHAND_RIGHT"
                               },
                      "type":  "HandOffTurnAssignment"
                  },
                  {
                      "exported":  "true",
                      "guid":  "e9e6db1b-4ac9-4f84-90f6-2126c4f9b216",
                      "data":  {
                                   "handoffExit":  "EXITTYPE_DROPBACK",
                                   "opCodeEX":  "ID_HANDOFF_GIVE",
                                   "playerNum":  "1",
                                   "handoffRun":  "RUNTYPE_HANDOUT"
                               },
                      "type":  "HandOffGiveAssignment"
                  },
                  {
                      "exported":  "true",
                      "guid":  "3a56b46b-6f60-4d4a-8b78-23e3ffb9674f",
                      "data":  {
                                   "opCodeEX":  "ID_SCRAMBLE",
                                   "direction":  "0",
                                   "distance":  "0",
                                   "dropBackType":  "DROP_TYPEENUM_NONEVALUE"
                               },
                      "type":  "QBScrambleAssignment"
                  },
                  {
                      "exported":  "true",
                      "guid":  "5fd899b7-ceb2-4d65-bc15-40f805874771",
                      "data":  {
                                   "opCodeEX":  "ID_NONE"
                               },
                      "type":  "NoneAssignment"
                  },
                  {
                      "exported":  "true",
                      "guid":  "cf53be0a-0a15-4531-95e2-239475c6771f",
                      "data":  {
                                   "opCodeEX":  "ID_NONE"
                               },
                      "type":  "NoneAssignment"
                  }
              ],
    "name":  "football/Gameplay/playbooks/PlayLibrary/Assignments/Precan/QB_UC_HB_InsideZoneLt_BootRt_RPO_Alert"
}
